vbox_sdk-5.1.18.post0.dist-info/DESCRIPTION.rst
vbox_sdk-5.1.18.post0.dist-info/METADATA
vbox_sdk-5.1.18.post0.dist-info/RECORD
vbox_sdk-5.1.18.post0.dist-info/WHEEL
vbox_sdk-5.1.18.post0.dist-info/metadata.json
vbox_sdk-5.1.18.post0.dist-info/top_level.txt
vboxapi/VirtualBox_constants.py
vboxapi/__init__.py
