Metadata-Version: 2.0
Name: vbox-sdk
Version: 5.1.18-0
Summary: The VirtualBox Software Developer Kit as available from https://www.virtualbox.org/wiki/Downloads
Home-page: https://github.com/mmabey/vbox_sdk
Author: Mike Mabey
Author-email: mmabey@ieee.org
License: Unlicense
Download-URL: https://github.com/mmabey/vbox_sdk/archive/v5.1.18.tar.gz
Keywords: vbox,vbox api,vbox sdk,VirtualBox,Oracle,virtual machine manager
Platform: UNKNOWN
Classifier: Intended Audience :: Developers
Classifier: Operating System :: POSIX
Classifier: Operating System :: POSIX :: Linux
Classifier: Operating System :: Microsoft :: Windows
Classifier: Operating System :: MacOS
Classifier: Programming Language :: Python :: 2.7
